README.md
setup.py
hifipower/__init__.py
hifipower/driver.py
hifipower/main.py
hifipower.egg-info/PKG-INFO
hifipower.egg-info/SOURCES.txt
hifipower.egg-info/dependency_links.txt
hifipower.egg-info/entry_points.txt
hifipower.egg-info/requires.txt
hifipower.egg-info/top_level.txt
hifipower.egg-info/zip-safe