Metadata-Version: 1.1
Name: hifipower
Version: 0.2b11
Summary: On/off control via web API for hi-fi audio equipment
Home-page: http://github.com/elegantandrogyne/hifipower
Author: Keri Szafir
Author-email: keri.szafir@gmail.com
License: MIT
Platform: UNKNOWN
Classifier: Development Status :: 4 - Beta
Classifier: Topic :: System :: Hardware :: Hardware Drivers
Classifier: License :: OSI Approved :: MIT License
Classifier: Natural Language :: English
Classifier: Operating System :: POSIX :: Linux
Classifier: Programming Language :: Python :: 3 :: Only
Classifier: Framework :: Flask
